{"businesses": [{"id": "HjVWEksLViNeFze6QiFbrw", "alias": "howe-sound-inn-and-brewing-co-squamish", "name": "Howe Sound Inn & Brewing Co.", "image_url": "https://s3-media4.fl.yelpcdn.com/bphoto/5SWat7Qrpl3KgWUS0Bk4Jw/o.jpg", "is_closed": false, "url": "https://www.yelp.com/biz/howe-sound-inn-and-brewing-co-squamish?adjust_creative=caQpq7D94Y91yZnfu7m19Q&utm_campaign=yelp_api_v3&utm_medium=api_v3_business_search&utm_source=caQpq7D94Y91yZnfu7m19Q", "review_count": 192, "categories": [{"alias": "brewpubs", "title": "Brewpubs"}], "rating": 3.5, "coordinates": {"latitude": 49.69573, "longitude": -123.15632}, "transactions": [], "price": "$$", "location": {"address1": "37801 Cleveland Avenue", "address2": "", "address3": "", "city": "Squamish", "zip_code": "V8B 0A7", "country": "CA", "state": "BC", "display_address": ["37801 Cleveland Avenue", "Squamish, BC V8B 0A7", "Canada"]}, "phone": "+16048922603", "display_phone": "+1 604-892-2603", "distance": 2676.4223609860187}, {"id": "TFjjEnE2AVZWMuqpMH9nBA", "alias": "zephyr-cafe-squamish", "name": "Zephyr Cafe", "image_url": "https://s3-media1.fl.yelpcdn.com/bphoto/tXTbMWQNjLrz7220DjptsA/o.jpg", "is_closed": false, "url": "https://www.yelp.com/biz/zephyr-cafe-squamish?adjust_creative=caQpq7D94Y91yZnfu7m19Q&utm_campaign=yelp_api_v3&utm_medium=api_v3_business_search&utm_source=caQpq7D94Y91yZnfu7m19Q", "review_count": 115, "categories": [{"alias": "coffee", "title": "Coffee & Tea"}, {"alias": "sandwiches", "title": "Sandwiches"}], "rating": 4.0, "coordinates": {"latitude": 49.699499, "longitude": -123.152203}, "transactions": [], "price": "$$", "location": {"address1": "38078 Cleveland Avenue", "address2": "", "address3": "", "city": "Squamish", "zip_code": "V8B 0A4", "country": "CA", "state": "BC", "display_address": ["38078 Cleveland Avenue", "Squamish, BC V8B 0A4", "Canada"]}, "phone": "+16045674568", "display_phone": "+1 604-567-4568", "distance": 2179.4096695384824}, {"id": "MApcFhCwsgoQGKVbPe3klQ", "alias": "the-salted-vine-kitchen-bar-squamish", "name": "The Salted Vine Kitchen + Bar", "image_url": "https://s3-media3.fl.yelpcdn.com/bphoto/doYqLR39C61FdKQ3ub3P4g/o.jpg", "is_closed": false, "url": "https://www.yelp.com/biz/the-salted-vine-kitchen-bar-squamish?adjust_creative=caQpq7D94Y91yZnfu7m19Q&utm_campaign=yelp_api_v3&utm_medium=api_v3_business_search&utm_source=caQpq7D94Y91yZnfu7m19Q", "review_count": 39, "categories": [{"alias": "cocktailbars", "title": "Cocktail Bars"}, {"alias": "seafood", "title": "Seafood"}, {"alias": "newcanadian", "title": "Canadian (New)"}], "rating": 4.5, "coordinates": {"latitude": 49.698569, "longitude": -123.1551884}, "transactions": [], "price": "$$$", "location": {"address1": "37991 Second Avenue", "address2": null, "address3": "", "city": "Squamish", "zip_code": "V8B 0R2", "country": "CA", "state": "BC", "display_address": ["37991 Second Avenue", "Squamish, BC V8B 0R2", "Canada"]}, "phone": "+16043901910", "display_phone": "+1 604-390-1910", "distance": 2331.6673669346123}, {"id": "nXN16mpi5zqpFuBKNg_G6Q", "alias": "backcountry-brewing-squamish", "name": "Backcountry Brewing", "image_url": "https://s3-media4.fl.yelpcdn.com/bphoto/43OST8N6b75wcjAIA8SIcg/o.jpg", "is_closed": false, "url": "https://www.yelp.com/biz/backcountry-brewing-squamish?adjust_creative=caQpq7D94Y91yZnfu7m19Q&utm_campaign=yelp_api_v3&utm_medium=api_v3_business_search&utm_source=caQpq7D94Y91yZnfu7m19Q", "review_count": 61, "categories": [{"alias": "pizza", "title": "Pizza"}, {"alias": "brewpubs", "title": "Brewpubs"}], "rating": 4.0, "coordinates": {"latitude": 49.723799, "longitude": -123.154237}, "transactions": [], "price": "$$", "location": {"address1": "405-1201 Commercial Way", "address2": "", "address3": null, "city": "Squamish", "zip_code": "V8B 0V1", "country": "CA", "state": "BC", "display_address": ["405-1201 Commercial Way", "Squamish, BC V8B 0V1", "Canada"]}, "phone": "+16045672739", "display_phone": "+1 604-567-2739", "distance": 815.1296953735438}, {"id": "xQWJ4g97FMJkA-wMdkRrsw", "alias": "a-frame-brewing-company-squamish-3", "name": "A FRAME Brewing Company", "image_url": "https://s3-media1.fl.yelpcdn.com/bphoto/EWhsKR4cPafuWBOp7jfzUw/o.jpg", "is_closed": false, "url": "https://www.yelp.com/biz/a-frame-brewing-company-squamish-3?adjust_creative=caQpq7D94Y91yZnfu7m19Q&utm_campaign=yelp_api_v3&utm_medium=api_v3_business_search&utm_source=caQpq7D94Y91yZnfu7m19Q", "review_count": 19, "categories": [{"alias": "breweries", "title": "Breweries"}], "rating": 4.5, "coordinates": {"latitude": 49.71744, "longitude": -123.15625}, "transactions": [], "price": "$$", "location": {"address1": "1-38927 Queens Way", "address2": null, "address3": "", "city": "Squamish", "zip_code": "V8B 0K9", "country": "CA", "state": "BC", "display_address": ["1-38927 Queens Way", "Squamish, BC V8B 0K9", "Canada"]}, "phone": "+16048920777", "display_phone": "+1 604-892-0777", "distance": 698.8324763621206}, {"id": "0pzB6xPi0lfIRBQzdCj5NA", "alias": "alice-brohm-ice-cream-squamish-2", "name": "Alice + Brohm Ice Cream", "image_url": "https://s3-media1.fl.yelpcdn.com/bphoto/qnxVXXa23lOj3Fmmby9AeQ/o.jpg", "is_closed": false, "url": "https://www.yelp.com/biz/alice-brohm-ice-cream-squamish-2?adjust_creative=caQpq7D94Y91yZnfu7m19Q&utm_campaign=yelp_api_v3&utm_medium=api_v3_business_search&utm_source=caQpq7D94Y91yZnfu7m19Q", "review_count": 19, "categories": [{"alias": "icecream", "title": "Ice Cream & Frozen Yogurt"}], "rating": 4.5, "coordinates": {"latitude": 49.73546845241754, "longitude": -123.13203544866376}, "transactions": [], "price": "$$", "location": {"address1": "1861 Mamquam Road", "address2": "Unit 9", "address3": "", "city": "Squamish", "zip_code": "V8B 0H5", "country": "CA", "state": "BC", "display_address": ["1861 Mamquam Road", "Unit 9", "Squamish, BC V8B 0H5", "Canada"]}, "phone": "+12505719978", "display_phone": "+1 250-571-9978", "distance": 2121.1443059835237}, {"id": "gOx-1bpg8Ix6GPj6WJJ1nA", "alias": "xoco-chocolate-squamish", "name": "Xoco Chocolate", "image_url": "https://s3-media4.fl.yelpcdn.com/bphoto/TYh9ougq4tiybIKyEnku-w/o.jpg", "is_closed": false, "url": "https://www.yelp.com/biz/xoco-chocolate-squamish?adjust_creative=caQpq7D94Y91yZnfu7m19Q&utm_campaign=yelp_api_v3&utm_medium=api_v3_business_search&utm_source=caQpq7D94Y91yZnfu7m19Q", "review_count": 13, "categories": [{"alias": "bakeries", "title": "Bakeries"}, {"alias": "chocolate", "title": "Chocolatiers & Shops"}], "rating": 5.0, "coordinates": {"latitude": 49.69868, "longitude": -123.15291}, "transactions": [], "price": "$$", "location": {"address1": "38020 Cleveland Ave", "address2": "", "address3": "", "city": "Squamish", "zip_code": "V8B 0A1", "country": "CA", "state": "BC", "display_address": ["38020 Cleveland Ave", "Squamish, BC V8B 0A1", "Canada"]}, "phone": "+16048929446", "display_phone": "+1 604-892-9446", "distance": 2287.1587573755355}, {"id": "679_Jl4i12h31tD5u77Klw", "alias": "gillespies-fine-spirits-squamish", "name": "Gillespie's Fine Spirits", "image_url": "https://s3-media1.fl.yelpcdn.com/bphoto/x84j8I-fzGhQqmMFHSVhEw/o.jpg", "is_closed": false, "url": "https://www.yelp.com/biz/gillespies-fine-spirits-squamish?adjust_creative=caQpq7D94Y91yZnfu7m19Q&utm_campaign=yelp_api_v3&utm_medium=api_v3_business_search&utm_source=caQpq7D94Y91yZnfu7m19Q", "review_count": 11, "categories": [{"alias": "distilleries", "title": "Distilleries"}, {"alias": "cocktailbars", "title": "Cocktail Bars"}], "rating": 4.5, "coordinates": {"latitude": 49.71522, "longitude": -123.14894}, "transactions": [], "price": "$$", "location": {"address1": "38918 Progress Way", "address2": "Unit 8", "address3": "", "city": "Squamish", "zip_code": "V8B 0K7", "country": "CA", "state": "BC", "display_address": ["38918 Progress Way", "Unit 8", "Squamish, BC V8B 0K7", "Canada"]}, "phone": "+16043901122", "display_phone": "+1 604-390-1122", "distance": 440.30958340990713}, {"id": "Ai9u1qW7mgV3z21hhgRkWg", "alias": "counterpart-coffee-squamish", "name": "Counterpart Coffee", "image_url": "https://s3-media4.fl.yelpcdn.com/bphoto/3ViwJ3APWAhfETALCbSW2Q/o.jpg", "is_closed": false, "url": "https://www.yelp.com/biz/counterpart-coffee-squamish?adjust_creative=caQpq7D94Y91yZnfu7m19Q&utm_campaign=yelp_api_v3&utm_medium=api_v3_business_search&utm_source=caQpq7D94Y91yZnfu7m19Q", "review_count": 8, "categories": [{"alias": "coffee", "title": "Coffee & Tea"}], "rating": 5.0, "coordinates": {"latitude": 49.7194813034038, "longitude": -123.149772525872}, "transactions": [], "price": "$", "location": {"address1": "39012 Discovery Way", "address2": "Suite 107", "address3": "", "city": "Squamish", "zip_code": "V8B 0R8", "country": "CA", "state": "BC", "display_address": ["39012 Discovery Way", "Suite 107", "Squamish, BC V8B 0R8", "Canada"]}, "phone": "+16045673338", "display_phone": "+1 604-567-3338", "distance": 278.3817030078304}, {"id": "GLjS9Ajp6rbZPuu36ikWhw", "alias": "shady-tree-neighborhood-pub-squamish", "name": "Shady Tree Neighborhood Pub", "image_url": "https://s3-media3.fl.yelpcdn.com/bphoto/uMKjmonzaTbix82-e4QPEw/o.jpg", "is_closed": false, "url": "https://www.yelp.com/biz/shady-tree-neighborhood-pub-squamish?adjust_creative=caQpq7D94Y91yZnfu7m19Q&utm_campaign=yelp_api_v3&utm_medium=api_v3_business_search&utm_source=caQpq7D94Y91yZnfu7m19Q", "review_count": 36, "categories": [{"alias": "pubs", "title": "Pubs"}], "rating": 3.5, "coordinates": {"latitude": 49.7423719951736, "longitude": -123.136316563131}, "transactions": [], "price": "$$", "location": {"address1": "40456 Government Road", "address2": null, "address3": "", "city": "Squamish", "zip_code": "V0N 1T0", "country": "CA", "state": "BC", "display_address": ["40456 Government Road", "Squamish, BC V0N 1T0", "Canada"]}, "phone": "+16048981571", "display_phone": "+1 604-898-1571", "distance": 2724.761432863849}, {"id": "PcFAmG2iZyqbIjvk87MlJg", "alias": "caffe-garibaldi-squamish", "name": "Caffe Garibaldi", "image_url": "https://s3-media3.fl.yelpcdn.com/bphoto/al8K12I2w1J2xFEB8HazxQ/o.jpg", "is_closed": false, "url": "https://www.yelp.com/biz/caffe-garibaldi-squamish?adjust_creative=caQpq7D94Y91yZnfu7m19Q&utm_campaign=yelp_api_v3&utm_medium=api_v3_business_search&utm_source=caQpq7D94Y91yZnfu7m19Q", "review_count": 11, "categories": [{"alias": "bakeries", "title": "Bakeries"}, {"alias": "cafes", "title": "Cafes"}], "rating": 4.5, "coordinates": {"latitude": 49.70738, "longitude": -123.14587}, "transactions": [], "price": "$", "location": {"address1": "38551 Loggers Lane", "address2": "", "address3": "", "city": "Squamish", "zip_code": "V8B 0H2", "country": "CA", "state": "BC", "display_address": ["38551 Loggers Lane", "Squamish, BC V8B 0H2", "Canada"]}, "phone": "", "display_phone": "", "distance": 1299.4645534870438}, {"id": "bu8kludo5xog-L8SATm9Gg", "alias": "golden-crust-squamish", "name": "Golden Crust", "image_url": "https://s3-media1.fl.yelpcdn.com/bphoto/otojO0oQBgHgL4_FovFPtQ/o.jpg", "is_closed": false, "url": "https://www.yelp.com/biz/golden-crust-squamish?adjust_creative=caQpq7D94Y91yZnfu7m19Q&utm_campaign=yelp_api_v3&utm_medium=api_v3_business_search&utm_source=caQpq7D94Y91yZnfu7m19Q", "review_count": 10, "categories": [{"alias": "bakeries", "title": "Bakeries"}, {"alias": "desserts", "title": "Desserts"}], "rating": 4.5, "coordinates": {"latitude": 49.7164, "longitude": -123.15618}, "transactions": [], "price": "$$", "location": {"address1": "38924 Queens Way", "address2": "Unit 5", "address3": "", "city": "Squamish", "zip_code": "V8B 0K8", "country": "CA", "state": "BC", "display_address": ["38924 Queens Way", "Unit 5", "Squamish, BC V8B 0K8", "Canada"]}, "phone": "+16048927437", "display_phone": "+1 604-892-7437", "distance": 761.1652917773939}, {"id": "2Wkv0_9RsoNyKyfmwcLA7Q", "alias": "the-locavore-squamish-2", "name": "The Locavore", "image_url": "https://s3-media1.fl.yelpcdn.com/bphoto/F3aVCs6pyMwKvJ_OUyr3VQ/o.jpg", "is_closed": false, "url": "https://www.yelp.com/biz/the-locavore-squamish-2?adjust_creative=caQpq7D94Y91yZnfu7m19Q&utm_campaign=yelp_api_v3&utm_medium=api_v3_business_search&utm_source=caQpq7D94Y91yZnfu7m19Q", "review_count": 22, "categories": [{"alias": "foodtrucks", "title": "Food Trucks"}], "rating": 4.0, "coordinates": {"latitude": 49.7354003573313, "longitude": -123.131822261774}, "transactions": [], "price": "$$", "location": {"address1": "Squamish Town Hub", "address2": "1861 Mamquam Road", "address3": "", "city": "Squamish", "zip_code": "V8B 0G2", "country": "CA", "state": "BC", "display_address": ["Squamish Town Hub", "1861 Mamquam Road", "Squamish, BC V8B 0G2", "Canada"]}, "phone": "+16045675646", "display_phone": "+1 604-567-5646", "distance": 2121.8572154716103}, {"id": "KHgSEeqSOA_0PyRKY0VuYA", "alias": "1914-coffee-squamish", "name": "1914 Coffee", "image_url": "https://s3-media1.fl.yelpcdn.com/bphoto/2GnjrJRL87GRGJGVw_f1Pg/o.jpg", "is_closed": false, "url": "https://www.yelp.com/biz/1914-coffee-squamish?adjust_creative=caQpq7D94Y91yZnfu7m19Q&utm_campaign=yelp_api_v3&utm_medium=api_v3_business_search&utm_source=caQpq7D94Y91yZnfu7m19Q", "review_count": 17, "categories": [{"alias": "coffee", "title": "Coffee & Tea"}], "rating": 4.0, "coordinates": {"latitude": 49.7008346, "longitude": -123.1533593}, "transactions": [], "price": "$$", "location": {"address1": "38123 2nd Avenue", "address2": "", "address3": "", "city": "Squamish", "zip_code": "V8B 0C4", "country": "CA", "state": "BC", "display_address": ["38123 2nd Avenue", "Squamish, BC V8B 0C4", "Canada"]}, "phone": "", "display_phone": "", "distance": 2048.5876551777433}, {"id": "ga4Iu4n-yYXuONWiAVsinA", "alias": "tim-hortons-squamish-2", "name": "Tim Horton's", "image_url": "https://s3-media2.fl.yelpcdn.com/bphoto/yD8Vv1nUdIATjKDnxPsfkg/o.jpg", "is_closed": false, "url": "https://www.yelp.com/biz/tim-hortons-squamish-2?adjust_creative=caQpq7D94Y91yZnfu7m19Q&utm_campaign=yelp_api_v3&utm_medium=api_v3_business_search&utm_source=caQpq7D94Y91yZnfu7m19Q", "review_count": 28, "categories": [{"alias": "coffee", "title": "Coffee & Tea"}, {"alias": "bakeries", "title": "Bakeries"}], "rating": 3.5, "coordinates": {"latitude": 49.740823, "longitude": -123.1367254}, "transactions": [], "price": "$", "location": {"address1": "38930 Progress Way", "address2": "", "address3": "", "city": "Squamish", "zip_code": "V0N 3G0", "country": "CA", "state": "BC", "display_address": ["38930 Progress Way", "Squamish, BC V0N 3G0", "Canada"]}, "phone": "+16048154311", "display_phone": "+1 604-815-4311", "distance": 2550.823465272348}, {"id": "kaGujRBgddHt3oh0gY8R4A", "alias": "geo-cider-squamish", "name": "Geo Cider", "image_url": "https://s3-media2.fl.yelpcdn.com/bphoto/ceZ5mL0x7ZEDzJpcOC1JIQ/o.jpg", "is_closed": false, "url": "https://www.yelp.com/biz/geo-cider-squamish?adjust_creative=caQpq7D94Y91yZnfu7m19Q&utm_campaign=yelp_api_v3&utm_medium=api_v3_business_search&utm_source=caQpq7D94Y91yZnfu7m19Q", "review_count": 9, "categories": [{"alias": "cideries", "title": "Cideries"}, {"alias": "gastropubs", "title": "Gastropubs"}], "rating": 4.5, "coordinates": {"latitude": 49.7242497362148, "longitude": -123.15430348377}, "transactions": [], "location": {"address1": "318 - 1201 Commercial Way", "address2": null, "address3": "", "city": "Squamish", "zip_code": "V8B 0V1", "country": "CA", "state": "BC", "display_address": ["318 - 1201 Commercial Way", "Squamish, BC V8B 0V1", "Canada"]}, "phone": "+17787331080", "display_phone": "+1 778-733-1080", "distance": 854.0677280862958}, {"id": "tU1pyjzC1JF02C1yKS1s6g", "alias": "lucas-teas-squamish", "name": "Lucas Teas", "image_url": "https://s3-media3.fl.yelpcdn.com/bphoto/FGPtnYGeG2zqbwTQoybuNw/o.jpg", "is_closed": false, "url": "https://www.yelp.com/biz/lucas-teas-squamish?adjust_creative=caQpq7D94Y91yZnfu7m19Q&utm_campaign=yelp_api_v3&utm_medium=api_v3_business_search&utm_source=caQpq7D94Y91yZnfu7m19Q", "review_count": 6, "categories": [{"alias": "coffee", "title": "Coffee & Tea"}], "rating": 5.0, "coordinates": {"latitude": 49.6987305, "longitude": -123.1528625}, "transactions": [], "location": {"address1": "38028 Cleveland Ave", "address2": "", "address3": "", "city": "Squamish", "zip_code": "V8B 0J2", "country": "CA", "state": "BC", "display_address": ["38028 Cleveland Ave", "Squamish, BC V8B 0J2", "Canada"]}, "phone": "+16045674577", "display_phone": "+1 604-567-4577", "distance": 2267.326997539902}, {"id": "AY788NPVfRijYo_cVtkhvg", "alias": "timberwolf-restaurant-and-lounge-squamish", "name": "Timberwolf Restaurant & Lounge", "image_url": "https://s3-media2.fl.yelpcdn.com/bphoto/VfSgDJQdOAxRyc9dCGebRw/o.jpg", "is_closed": false, "url": "https://www.yelp.com/biz/timberwolf-restaurant-and-lounge-squamish?adjust_creative=caQpq7D94Y91yZnfu7m19Q&utm_campaign=yelp_api_v3&utm_medium=api_v3_business_search&utm_source=caQpq7D94Y91yZnfu7m19Q", "review_count": 21, "categories": [{"alias": "newcanadian", "title": "Canadian (New)"}, {"alias": "lounges", "title": "Lounges"}], "rating": 3.5, "coordinates": {"latitude": 49.71604, "longitude": -123.14892}, "transactions": [], "price": "$$", "location": {"address1": "38922 Progress Way", "address2": "", "address3": "", "city": "Squamish", "zip_code": "V8B 0K5", "country": "CA", "state": "BC", "display_address": ["38922 Progress Way", "Squamish, BC V8B 0K5", "Canada"]}, "phone": "+16048154424", "display_phone": "+1 604-815-4424", "distance": 348.17350165027614}, {"id": "P-qJzOyhaoQjymyo5JPY-Q", "alias": "tall-tree-bakery-squamish", "name": "Tall Tree Bakery", "image_url": "https://s3-media4.fl.yelpcdn.com/bphoto/b_r-Fbb2wdsegT6cvuRObA/o.jpg", "is_closed": false, "url": "https://www.yelp.com/biz/tall-tree-bakery-squamish?adjust_creative=caQpq7D94Y91yZnfu7m19Q&utm_campaign=yelp_api_v3&utm_medium=api_v3_business_search&utm_source=caQpq7D94Y91yZnfu7m19Q", "review_count": 12, "categories": [{"alias": "bakeries", "title": "Bakeries"}], "rating": 4.5, "coordinates": {"latitude": 49.72399, "longitude": -123.154161}, "transactions": [], "price": "$$", "location": {"address1": "1201 Commercial Way", "address2": "Suite 404", "address3": null, "city": "Squamish", "zip_code": "V8B 0V1", "country": "CA", "state": "BC", "display_address": ["1201 Commercial Way", "Suite 404", "Squamish, BC V8B 0V1", "Canada"]}, "phone": "+16048490951", "display_phone": "+1 604-849-0951", "distance": 826.2074767354727}, {"id": "bY2ICAk7Ah1xyOZ5u84YuA", "alias": "mcdonalds-squamish", "name": "McDonald's", "image_url": "https://s3-media3.fl.yelpcdn.com/bphoto/gGOAZOoY04RV168bDZmscQ/o.jpg", "is_closed": false, "url": "https://www.yelp.com/biz/mcdonalds-squamish?adjust_creative=caQpq7D94Y91yZnfu7m19Q&utm_campaign=yelp_api_v3&utm_medium=api_v3_business_search&utm_source=caQpq7D94Y91yZnfu7m19Q", "review_count": 15, "categories": [{"alias": "hotdogs", "title": "Fast Food"}, {"alias": "burgers", "title": "Burgers"}, {"alias": "coffee", "title": "Coffee & Tea"}], "rating": 3.5, "coordinates": {"latitude": 49.7046948163349, "longitude": -123.146693516518}, "transactions": [], "price": "$", "location": {"address1": "38451 Cleveland Avenue", "address2": "", "address3": "", "city": "Squamish", "zip_code": "V8B 0E4", "country": "CA", "state": "BC", "display_address": ["38451 Cleveland Avenue", "Squamish, BC V8B 0E4", "Canada"]}, "phone": "+16048925937", "display_phone": "+1 604-892-5937", "distance": 1557.546437826026}, {"id": "fW1PRRziMg6cf2nrJtaawA", "alias": "sunflower-bakery-and-cafe-squamish", "name": "Sunflower Bakery & Cafe", "image_url": "https://s3-media3.fl.yelpcdn.com/bphoto/CKKtDXnV5kSLV_Vr2ZnyJg/o.jpg", "is_closed": false, "url": "https://www.yelp.com/biz/sunflower-bakery-and-cafe-squamish?adjust_creative=caQpq7D94Y91yZnfu7m19Q&utm_campaign=yelp_api_v3&utm_medium=api_v3_business_search&utm_source=caQpq7D94Y91yZnfu7m19Q", "review_count": 19, "categories": [{"alias": "bakeries", "title": "Bakeries"}, {"alias": "breakfast_brunch", "title": "Breakfast & Brunch"}, {"alias": "cafes", "title": "Cafes"}], "rating": 3.5, "coordinates": {"latitude": 49.69969, "longitude": -123.15204}, "transactions": [], "price": "$", "location": {"address1": "38086 Cleveland Ave", "address2": null, "address3": "", "city": "Squamish", "zip_code": "V8B 0B7", "country": "CA", "state": "BC", "display_address": ["38086 Cleveland Ave", "Squamish, BC V8B 0B7", "Canada"]}, "phone": "+16048922231", "display_phone": "+1 604-892-2231", "distance": 2160.0553711655607}, {"id": "0ziVRetrrAKNZ87nvTCJRA", "alias": "save-on-foods-squamish", "name": "Save-On-Foods", "image_url": "https://s3-media4.fl.yelpcdn.com/bphoto/RW1_G-1xfVHhf4KvuTXb7w/o.jpg", "is_closed": false, "url": "https://www.yelp.com/biz/save-on-foods-squamish?adjust_creative=caQpq7D94Y91yZnfu7m19Q&utm_campaign=yelp_api_v3&utm_medium=api_v3_business_search&utm_source=caQpq7D94Y91yZnfu7m19Q", "review_count": 7, "categories": [{"alias": "grocery", "title": "Grocery"}, {"alias": "pharmacy", "title": "Pharmacy"}], "rating": 4.5, "coordinates": {"latitude": 49.703244047460124, "longitude": -123.15172791481018}, "transactions": [], "price": "$$", "location": {"address1": "1301 Pemberton", "address2": "", "address3": "", "city": "Squamish", "zip_code": "V8B 0A1", "country": "CA", "state": "BC", "display_address": ["1301 Pemberton", "Squamish, BC V8B 0A1", "Canada"]}, "phone": "+16048925976", "display_phone": "+1 604-892-5976", "distance": 1765.3562625519485}, {"id": "OvIxIvELfdq7blWGS9h6VQ", "alias": "squamish-farmers-market-squamish", "name": "Squamish Farmers' Market", "image_url": "https://s3-media4.fl.yelpcdn.com/bphoto/86K2hU9XyNKsMHfwyG339g/o.jpg", "is_closed": false, "url": "https://www.yelp.com/biz/squamish-farmers-market-squamish?adjust_creative=caQpq7D94Y91yZnfu7m19Q&utm_campaign=yelp_api_v3&utm_medium=api_v3_business_search&utm_source=caQpq7D94Y91yZnfu7m19Q", "review_count": 5, "categories": [{"alias": "farmersmarket", "title": "Farmers Market"}], "rating": 4.5, "coordinates": {"latitude": 49.69816, "longitude": -123.15337}, "transactions": [], "price": "$$", "location": {"address1": "37996 Cleveland Avenue", "address2": "", "address3": "", "city": "Squamish", "zip_code": "V8B 0R2", "country": "CA", "state": "BC", "display_address": ["37996 Cleveland Avenue", "Squamish, BC V8B 0R2", "Canada"]}, "phone": "+16048484339", "display_phone": "+1 604-848-4339", "distance": 2342.890698814106}, {"id": "pZcYeHH-Vn7htdAyY2EJ0A", "alias": "bisla-squamish-2", "name": "Bisla", "image_url": "https://s3-media2.fl.yelpcdn.com/bphoto/fzmSvobTlKzvd3BRXcXxOQ/o.jpg", "is_closed": false, "url": "https://www.yelp.com/biz/bisla-squamish-2?adjust_creative=caQpq7D94Y91yZnfu7m19Q&utm_campaign=yelp_api_v3&utm_medium=api_v3_business_search&utm_source=caQpq7D94Y91yZnfu7m19Q", "review_count": 18, "categories": [{"alias": "indpak", "title": "Indian"}, {"alias": "desserts", "title": "Desserts"}, {"alias": "beer_and_wine", "title": "Beer, Wine & Spirits"}], "rating": 3.5, "coordinates": {"latitude": 49.7016895261434, "longitude": -123.15207230105}, "transactions": [], "price": "$$", "location": {"address1": "1345 Pemberton Avenue", "address2": "", "address3": "", "city": "Squamish", "zip_code": "V8B 0J8", "country": "CA", "state": "BC", "display_address": ["1345 Pemberton Avenue", "Squamish, BC V8B 0J8", "Canada"]}, "phone": "+16045675552", "display_phone": "+1 604-567-5552", "distance": 1939.3454323490168}, {"id": "fHn95L9aocj-Lf0PlTsiVw", "alias": "starbucks-squamish-2", "name": "Starbucks", "image_url": "https://s3-media2.fl.yelpcdn.com/bphoto/kOXucueMPZrSNgrFC-UTlA/o.jpg", "is_closed": false, "url": "https://www.yelp.com/biz/starbucks-squamish-2?adjust_creative=caQpq7D94Y91yZnfu7m19Q&utm_campaign=yelp_api_v3&utm_medium=api_v3_business_search&utm_source=caQpq7D94Y91yZnfu7m19Q", "review_count": 10, "categories": [{"alias": "coffee", "title": "Coffee & Tea"}], "rating": 3.5, "coordinates": {"latitude": 49.7360878, "longitude": -123.1330338}, "transactions": [], "price": "$", "location": {"address1": "40147 Glenalder Place", "address2": "", "address3": "", "city": "Squamish", "zip_code": "V8B 0G2", "country": "CA", "state": "BC", "display_address": ["40147 Glenalder Place", "Squamish, BC V8B 0G2", "Canada"]}, "phone": "+16048989510", "display_phone": "+1 604-898-9510", "distance": 2168.5800902061396}, {"id": "bUeOuLwiGhLvWTd149T78A", "alias": "northyards-cider-squamish", "name": "Northyards Cider", "image_url": "https://s3-media1.fl.yelpcdn.com/bphoto/UJjMIwzRB72uyWyapOAnCA/o.jpg", "is_closed": false, "url": "https://www.yelp.com/biz/northyards-cider-squamish?adjust_creative=caQpq7D94Y91yZnfu7m19Q&utm_campaign=yelp_api_v3&utm_medium=api_v3_business_search&utm_source=caQpq7D94Y91yZnfu7m19Q", "review_count": 9, "categories": [{"alias": "cideries", "title": "Cideries"}], "rating": 4.0, "coordinates": {"latitude": 49.7192027432018, "longitude": -123.153776073618}, "transactions": [], "location": {"address1": "9-38936 Queensway", "address2": "", "address3": null, "city": "Squamish", "zip_code": "V8B 0K8", "country": "CA", "state": "BC", "display_address": ["9-38936 Queensway", "Squamish, BC V8B 0K8", "Canada"]}, "phone": "+16048152197", "display_phone": "+1 604-815-2197", "distance": 555.0429400515171}, {"id": "ONgmYUDvgr1mx6lfVpSMbA", "alias": "luz-tacos-squamish-2", "name": "Luz Tacos", "image_url": "https://s3-media2.fl.yelpcdn.com/bphoto/ARN6Gj-aoe-rYtIXdpiCeQ/o.jpg", "is_closed": false, "url": "https://www.yelp.com/biz/luz-tacos-squamish-2?adjust_creative=caQpq7D94Y91yZnfu7m19Q&utm_campaign=yelp_api_v3&utm_medium=api_v3_business_search&utm_source=caQpq7D94Y91yZnfu7m19Q", "review_count": 9, "categories": [{"alias": "mexican", "title": "Mexican"}, {"alias": "foodtrucks", "title": "Food Trucks"}], "rating": 4.0, "coordinates": {"latitude": 49.717443, "longitude": -123.156253}, "transactions": [], "location": {"address1": "38927 Queens Way", "address2": null, "address3": "", "city": "Squamish", "zip_code": "V8B 0K9", "country": "CA", "state": "BC", "display_address": ["38927 Queens Way", "Squamish, BC V8B 0K9", "Canada"]}, "phone": "+16048492188", "display_phone": "+1 604-849-2188", "distance": 715.1334297113402}, {"id": "brk_U0rPI6cteOWE6m5tUQ", "alias": "backyard-squamish", "name": "Backyard", "image_url": "https://s3-media1.fl.yelpcdn.com/bphoto/CAcWA_9qFBNmceefk4auHw/o.jpg", "is_closed": false, "url": "https://www.yelp.com/biz/backyard-squamish?adjust_creative=caQpq7D94Y91yZnfu7m19Q&utm_campaign=yelp_api_v3&utm_medium=api_v3_business_search&utm_source=caQpq7D94Y91yZnfu7m19Q", "review_count": 4, "categories": [{"alias": "pubs", "title": "Pubs"}, {"alias": "tradamerican", "title": "American (Traditional)"}], "rating": 4.5, "coordinates": {"latitude": 49.70198, "longitude": -123.13297}, "transactions": [], "location": {"address1": "1907 Maple Drive", "address2": null, "address3": "", "city": "Squamish", "zip_code": "V8B 0Y5", "country": "CA", "state": "BC", "display_address": ["1907 Maple Drive", "Squamish, BC V8B 0Y5", "Canada"]}, "phone": "+16043902226", "display_phone": "+1 604-390-2226", "distance": 2082.491303468179}, {"id": "DQnGrc5wZMVfEbkTCpz5rA", "alias": "fox-and-oak-squamish", "name": "Fox & Oak", "image_url": "https://s3-media2.fl.yelpcdn.com/bphoto/2XFvvZ-Y1dXrUgz5zr2zog/o.jpg", "is_closed": false, "url": "https://www.yelp.com/biz/fox-and-oak-squamish?adjust_creative=caQpq7D94Y91yZnfu7m19Q&utm_campaign=yelp_api_v3&utm_medium=api_v3_business_search&utm_source=caQpq7D94Y91yZnfu7m19Q", "review_count": 5, "categories": [{"alias": "donuts", "title": "Donuts"}, {"alias": "coffee", "title": "Coffee & Tea"}, {"alias": "coffeeroasteries", "title": "Coffee Roasteries"}], "rating": 4.0, "coordinates": {"latitude": 49.69673268161273, "longitude": -123.15498847454808}, "transactions": [], "location": {"address1": "1396 Main Street", "address2": "", "address3": null, "city": "Squamish", "zip_code": "V8B 0S8", "country": "CA", "state": "BC", "display_address": ["1396 Main Street", "Squamish, BC V8B 0S8", "Canada"]}, "phone": "+17788940879", "display_phone": "+1 778-894-0879", "distance": 2524.6354087783657}, {"id": "_BMQ1iTYYhjeSEWMf1F1Dw", "alias": "starbucks-squamish-3", "name": "Starbucks", "image_url": "https://s3-media1.fl.yelpcdn.com/bphoto/7Qt_iGtwp7unewHWdNIkNA/o.jpg", "is_closed": false, "url": "https://www.yelp.com/biz/starbucks-squamish-3?adjust_creative=caQpq7D94Y91yZnfu7m19Q&utm_campaign=yelp_api_v3&utm_medium=api_v3_business_search&utm_source=caQpq7D94Y91yZnfu7m19Q", "review_count": 8, "categories": [{"alias": "coffee", "title": "Coffee & Tea"}], "rating": 3.5, "coordinates": {"latitude": 49.70363318040046, "longitude": -123.14611416244979}, "transactions": [], "price": "$", "location": {"address1": "1200 Hunter Place", "address2": "Suite 510", "address3": "", "city": "Squamish", "zip_code": "V8B 0G8", "country": "CA", "state": "BC", "display_address": ["1200 Hunter Place", "Suite 510", "Squamish, BC V8B 0G8", "Canada"]}, "phone": "+16048154334", "display_phone": "+1 604-815-4334", "distance": 1675.0013005781088}, {"id": "o-ZLZlbKKIiIVOeme2APEw", "alias": "cliffside-cider-squamish", "name": "Cliffside Cider", "image_url": "https://s3-media3.fl.yelpcdn.com/bphoto/vlqLoWFI-01wGp6cYbLH5Q/o.jpg", "is_closed": false, "url": "https://www.yelp.com/biz/cliffside-cider-squamish?adjust_creative=caQpq7D94Y91yZnfu7m19Q&utm_campaign=yelp_api_v3&utm_medium=api_v3_business_search&utm_source=caQpq7D94Y91yZnfu7m19Q", "review_count": 6, "categories": [{"alias": "cideries", "title": "Cideries"}], "rating": 4.0, "coordinates": {"latitude": 49.6949431617561, "longitude": -123.157672350435}, "transactions": [], "location": {"address1": "37760 2nd Avenue", "address2": "Unit 103", "address3": null, "city": "Squamish", "zip_code": "V6B 0A7", "country": "CA", "state": "BC", "display_address": ["37760 2nd Avenue", "Unit 103", "Squamish, BC V6B 0A7", "Canada"]}, "phone": "+17782295082", "display_phone": "+1 778-229-5082", "distance": 2769.3772206914286}, {"id": "BMaFQYf3m-UwL-pE3fHV_g", "alias": "squamish-liquor-store-squamish", "name": "Squamish Liquor Store", "image_url": "https://s3-media1.fl.yelpcdn.com/bphoto/qurAEmgx2YnG_uFUeUnAjQ/o.jpg", "is_closed": false, "url": "https://www.yelp.com/biz/squamish-liquor-store-squamish?adjust_creative=caQpq7D94Y91yZnfu7m19Q&utm_campaign=yelp_api_v3&utm_medium=api_v3_business_search&utm_source=caQpq7D94Y91yZnfu7m19Q", "review_count": 3, "categories": [{"alias": "beer_and_wine", "title": "Beer, Wine & Spirits"}], "rating": 4.5, "coordinates": {"latitude": 49.7022513, "longitude": -123.1503603}, "transactions": [], "price": "$$", "location": {"address1": "38241 Cleveland Ave", "address2": null, "address3": "", "city": "Squamish", "zip_code": "V0N 3G0", "country": "CA", "state": "BC", "display_address": ["38241 Cleveland Ave", "Squamish, BC V0N 3G0", "Canada"]}, "phone": "+16048988980", "display_phone": "+1 604-898-8980", "distance": 1854.1954686341453}, {"id": "0eGPCYL5sDUIREJdTaeKTw", "alias": "norman-rudys-squamish-2", "name": "Norman Rudy's", "image_url": "https://s3-media1.fl.yelpcdn.com/bphoto/LHwfVdlT8xOQhUftaJqa6w/o.jpg", "is_closed": false, "url": "https://www.yelp.com/biz/norman-rudys-squamish-2?adjust_creative=caQpq7D94Y91yZnfu7m19Q&utm_campaign=yelp_api_v3&utm_medium=api_v3_business_search&utm_source=caQpq7D94Y91yZnfu7m19Q", "review_count": 16, "categories": [{"alias": "pubs", "title": "Pubs"}, {"alias": "tradamerican", "title": "American (Traditional)"}, {"alias": "breakfast_brunch", "title": "Breakfast & Brunch"}], "rating": 3.0, "coordinates": {"latitude": 49.74933, "longitude": -123.13495}, "transactions": [], "price": "$$", "location": {"address1": "40900 Tantalus Road", "address2": null, "address3": "", "city": "Squamish", "zip_code": "V8B 0R3", "country": "CA", "state": "BC", "display_address": ["40900 Tantalus Road", "Squamish, BC V8B 0R3", "Canada"]}, "phone": "+18888237932", "display_phone": "+1 888-823-7932", "distance": 3533.3718155485344}, {"id": "UVoUY6Sa_333--kKDkym0g", "alias": "the-green-moustache-organic-caf\u00e9-squamish", "name": "The Green Moustache Organic Caf\u00e9", "image_url": "https://s3-media1.fl.yelpcdn.com/bphoto/FxuOk6NWGI2OIs6SAZ7V3g/o.jpg", "is_closed": false, "url": "https://www.yelp.com/biz/the-green-moustache-organic-caf%C3%A9-squamish?adjust_creative=caQpq7D94Y91yZnfu7m19Q&utm_campaign=yelp_api_v3&utm_medium=api_v3_business_search&utm_source=caQpq7D94Y91yZnfu7m19Q", "review_count": 5, "categories": [{"alias": "gluten_free", "title": "Gluten-Free"}, {"alias": "juicebars", "title": "Juice Bars & Smoothies"}, {"alias": "vegan", "title": "Vegan"}], "rating": 3.5, "coordinates": {"latitude": 49.7005463, "longitude": -123.1531571}, "transactions": [], "price": "$$", "location": {"address1": "38114 Second Avenue", "address2": null, "address3": "", "city": "Squamish", "zip_code": "V8B 0C4", "country": "CA", "state": "BC", "display_address": ["38114 Second Avenue", "Squamish, BC V8B 0C4", "Canada"]}, "phone": "+16048981134", "display_phone": "+1 604-898-1134", "distance": 2066.0663453017123}, {"id": "aVp7HTLzSeWbZbr8QDAP7g", "alias": "nesters-market-squamish", "name": "Nesters Market", "image_url": "https://s3-media2.fl.yelpcdn.com/bphoto/8S1NAs-DpjfcxxrlQHWCNQ/o.jpg", "is_closed": false, "url": "https://www.yelp.com/biz/nesters-market-squamish?adjust_creative=caQpq7D94Y91yZnfu7m19Q&utm_campaign=yelp_api_v3&utm_medium=api_v3_business_search&utm_source=caQpq7D94Y91yZnfu7m19Q", "review_count": 6, "categories": [{"alias": "grocery", "title": "Grocery"}], "rating": 3.5, "coordinates": {"latitude": 49.70344495586908, "longitude": -123.14685241461815}, "transactions": [], "price": "$$", "location": {"address1": "710 - 1200 Hunter Place", "address2": "", "address3": "", "city": "Squamish", "zip_code": "V8B 0G8", "country": "CA", "state": "BC", "display_address": ["710 - 1200 Hunter Place", "Squamish, BC V8B 0G8", "Canada"]}, "phone": "+16048150733", "display_phone": "+1 604-815-0733", "distance": 1696.8039112478994}, {"id": "9_cCjiRcnJeNZPUB9pDfmw", "alias": "booster-juice-squamish", "name": "Booster Juice", "image_url": "https://s3-media3.fl.yelpcdn.com/bphoto/dSr8KsPohkYQDQAdOitjaw/o.jpg", "is_closed": false, "url": "https://www.yelp.com/biz/booster-juice-squamish?adjust_creative=caQpq7D94Y91yZnfu7m19Q&utm_campaign=yelp_api_v3&utm_medium=api_v3_business_search&utm_source=caQpq7D94Y91yZnfu7m19Q", "review_count": 6, "categories": [{"alias": "juicebars", "title": "Juice Bars & Smoothies"}], "rating": 3.0, "coordinates": {"latitude": 49.7375674, "longitude": -123.1334926}, "transactions": [], "price": "$", "location": {"address1": "40230 Glenalder Place", "address2": "Unit C 7", "address3": null, "city": "Squamish", "zip_code": "V8B 0G2", "country": "CA", "state": "BC", "display_address": ["40230 Glenalder Place", "Unit C 7", "Squamish, BC V8B 0G2", "Canada"]}, "phone": "+16045671955", "display_phone": "+1 604-567-1955", "distance": 2365.7302146297097}, {"id": "v9VuS2C18ioFNjFyNB3F_w", "alias": "bean-around-the-world-brackendale", "name": "Bean Around the World", "image_url": "https://s3-media4.fl.yelpcdn.com/bphoto/ej8ERFa6RlaE3M60L8-XqQ/o.jpg", "is_closed": false, "url": "https://www.yelp.com/biz/bean-around-the-world-brackendale?adjust_creative=caQpq7D94Y91yZnfu7m19Q&utm_campaign=yelp_api_v3&utm_medium=api_v3_business_search&utm_source=caQpq7D94Y91yZnfu7m19Q", "review_count": 14, "categories": [{"alias": "coffee", "title": "Coffee & Tea"}], "rating": 4.0, "coordinates": {"latitude": 49.7577724599159, "longitude": -123.14153693708}, "transactions": [], "price": "$", "location": {"address1": "3 - 41340 Government Raod", "address2": "", "address3": "", "city": "Brackendale", "zip_code": "V0N 1H0", "country": "CA", "state": "BC", "display_address": ["3 - 41340 Government Raod", "Brackendale, BC V0N 1H0", "Canada"]}, "phone": "+16048982669", "display_phone": "+1 604-898-2669", "distance": 4357.336503477496}, {"id": "y9IM6Vlkla6428TpRJ8NuA", "alias": "daniels-fruit-stand-squamish-3", "name": "Daniel's Fruit Stand", "image_url": "https://s3-media1.fl.yelpcdn.com/bphoto/w03Sy5hD-7KY4-UO216yfw/o.jpg", "is_closed": false, "url": "https://www.yelp.com/biz/daniels-fruit-stand-squamish-3?adjust_creative=caQpq7D94Y91yZnfu7m19Q&utm_campaign=yelp_api_v3&utm_medium=api_v3_business_search&utm_source=caQpq7D94Y91yZnfu7m19Q", "review_count": 3, "categories": [{"alias": "farmersmarket", "title": "Farmers Market"}], "rating": 3.5, "coordinates": {"latitude": 49.7364374, "longitude": -123.1335637}, "transactions": [], "price": "$", "location": {"address1": "1851 Mamquam Rd", "address2": null, "address3": "", "city": "Squamish", "zip_code": "V0N 1T0", "country": "CA", "state": "BC", "display_address": ["1851 Mamquam Rd", "Squamish, BC V0N 1T0", "Canada"]}, "phone": "+17782660040", "display_phone": "+1 778-266-0040", "distance": 2168.5800902061396}, {"id": "rex4SBYc9ujovKn8bmCiqA", "alias": "narwhals-ice-cream-squamish", "name": "Narwhals Ice Cream", "image_url": "", "is_closed": false, "url": "https://www.yelp.com/biz/narwhals-ice-cream-squamish?adjust_creative=caQpq7D94Y91yZnfu7m19Q&utm_campaign=yelp_api_v3&utm_medium=api_v3_business_search&utm_source=caQpq7D94Y91yZnfu7m19Q", "review_count": 1, "categories": [{"alias": "icecream", "title": "Ice Cream & Frozen Yogurt"}], "rating": 5.0, "coordinates": {"latitude": 49.69854, "longitude": -123.15505}, "transactions": [], "location": {"address1": "38220 Highway 99", "address2": null, "address3": "", "city": "Squamish", "zip_code": "V8B 0A5", "country": "CA", "state": "BC", "display_address": ["38220 Highway 99", "Squamish, BC V8B 0A5", "Canada"]}, "phone": "+17783027465", "display_phone": "+1 778-302-7465", "distance": 1827.8894781312101}, {"id": "kKhZljKS7O3MTtYdCP0eqA", "alias": "2chill-squamish-gelato-spot-squamish", "name": "2Chill Squamish Gelato Spot", "image_url": "https://s3-media2.fl.yelpcdn.com/bphoto/vJepuUI9RZEXbN2pkpDrBQ/o.jpg", "is_closed": false, "url": "https://www.yelp.com/biz/2chill-squamish-gelato-spot-squamish?adjust_creative=caQpq7D94Y91yZnfu7m19Q&utm_campaign=yelp_api_v3&utm_medium=api_v3_business_search&utm_source=caQpq7D94Y91yZnfu7m19Q", "review_count": 3, "categories": [{"alias": "icecream", "title": "Ice Cream & Frozen Yogurt"}], "rating": 3.5, "coordinates": {"latitude": 49.69963, "longitude": -123.1521}, "transactions": [], "location": {"address1": "38084 Cleveland Avenue", "address2": null, "address3": "", "city": "Squamish", "zip_code": "V8B 0A1", "country": "CA", "state": "BC", "display_address": ["38084 Cleveland Avenue", "Squamish, BC V8B 0A1", "Canada"]}, "phone": "+16045672665", "display_phone": "+1 604-567-2665", "distance": 2179.200390056865}, {"id": "ECwI8544Kzkhu9VLgKKlUg", "alias": "scotties-liquor-store-squamish", "name": "Scotties Liquor Store", "image_url": "https://s3-media2.fl.yelpcdn.com/bphoto/WDmeHPSZKD_-SdnHyD_Bsw/o.jpg", "is_closed": false, "url": "https://www.yelp.com/biz/scotties-liquor-store-squamish?adjust_creative=caQpq7D94Y91yZnfu7m19Q&utm_campaign=yelp_api_v3&utm_medium=api_v3_business_search&utm_source=caQpq7D94Y91yZnfu7m19Q", "review_count": 3, "categories": [{"alias": "beer_and_wine", "title": "Beer, Wine & Spirits"}], "rating": 3.0, "coordinates": {"latitude": 49.6987114, "longitude": -123.1551208}, "transactions": [], "price": "$$", "location": {"address1": "37991 Second Avenue", "address2": "", "address3": "", "city": "Squamish", "zip_code": "V8B 0A8", "country": "CA", "state": "BC", "display_address": ["37991 Second Avenue", "Squamish, BC V8B 0A8", "Canada"]}, "phone": "+16048923422", "display_phone": "+1 604-892-3422", "distance": 2312.10997736929}, {"id": "yVfHlifR4rKSRQg7jg4oBQ", "alias": "7-eleven-squamish-2", "name": "7-Eleven", "image_url": "https://s3-media2.fl.yelpcdn.com/bphoto/gOhiyRVqi3c3AGoQB4JVMQ/o.jpg", "is_closed": false, "url": "https://www.yelp.com/biz/7-eleven-squamish-2?adjust_creative=caQpq7D94Y91yZnfu7m19Q&utm_campaign=yelp_api_v3&utm_medium=api_v3_business_search&utm_source=caQpq7D94Y91yZnfu7m19Q", "review_count": 2, "categories": [{"alias": "convenience", "title": "Convenience Stores"}, {"alias": "servicestations", "title": "Gas Stations"}, {"alias": "coffee", "title": "Coffee & Tea"}], "rating": 3.5, "coordinates": {"latitude": 49.7050878450184, "longitude": -123.146347}, "transactions": [], "price": "$", "location": {"address1": "38471 Cleveland Ave", "address2": "", "address3": "", "city": "Squamish", "zip_code": "V8B 0E4", "country": "CA", "state": "BC", "display_address": ["38471 Cleveland Ave", "Squamish, BC V8B 0E4", "Canada"]}, "phone": "+16048929286", "display_phone": "+1 604-892-9286", "distance": 1513.3578411082938}, {"id": "AeIp3ADovOMp_II9R5bEbQ", "alias": "base-camp-cafe-squamish", "name": "Base Camp Cafe", "image_url": "https://s3-media3.fl.yelpcdn.com/bphoto/tEd5ZYyH0eU3Nb_rt1aD0g/o.jpg", "is_closed": false, "url": "https://www.yelp.com/biz/base-camp-cafe-squamish?adjust_creative=caQpq7D94Y91yZnfu7m19Q&utm_campaign=yelp_api_v3&utm_medium=api_v3_business_search&utm_source=caQpq7D94Y91yZnfu7m19Q", "review_count": 1, "categories": [{"alias": "cafes", "title": "Cafes"}, {"alias": "bakeries", "title": "Bakeries"}], "rating": 5.0, "coordinates": {"latitude": 49.6751369752623, "longitude": -123.157064142133}, "transactions": [], "location": {"address1": "36800 Highway 99", "address2": "", "address3": "", "city": "Squamish", "zip_code": "V8B 0N2", "country": "CA", "state": "BC", "display_address": ["36800 Highway 99", "Squamish, BC V8B 0N2", "Canada"]}, "phone": "+16048922550", "display_phone": "+1 604-892-2550", "distance": 4907.460046763007}, {"id": "OG8q2uhrHrA5wbY_6b4qLA", "alias": "the-ledge-community-coffee-house-squamish", "name": "The Ledge Community Coffee House", "image_url": "https://s3-media4.fl.yelpcdn.com/bphoto/M4m57aBJqtGJ_RBXwfKaTQ/o.jpg", "is_closed": false, "url": "https://www.yelp.com/biz/the-ledge-community-coffee-house-squamish?adjust_creative=caQpq7D94Y91yZnfu7m19Q&utm_campaign=yelp_api_v3&utm_medium=api_v3_business_search&utm_source=caQpq7D94Y91yZnfu7m19Q", "review_count": 2, "categories": [{"alias": "coffee", "title": "Coffee & Tea"}, {"alias": "musicvenues", "title": "Music Venues"}, {"alias": "venues", "title": "Venues & Event Spaces"}], "rating": 3.0, "coordinates": {"latitude": 49.69946, "longitude": -123.15321}, "transactions": [], "price": "$$", "location": {"address1": "38055 Cleveland Avenue", "address2": "", "address3": null, "city": "Squamish", "zip_code": "V8B 0C3", "country": "CA", "state": "BC", "display_address": ["38055 Cleveland Avenue", "Squamish, BC V8B 0C3", "Canada"]}, "phone": "", "display_phone": "", "distance": 2199.6373873876723}, {"id": "Qhn3AKSSvE29tGUGcAgxHA", "alias": "independent-squamish", "name": "Independent", "image_url": "https://s3-media3.fl.yelpcdn.com/bphoto/FpNOPt9UbbAolSBGXRffxQ/o.jpg", "is_closed": false, "url": "https://www.yelp.com/biz/independent-squamish?adjust_creative=caQpq7D94Y91yZnfu7m19Q&utm_campaign=yelp_api_v3&utm_medium=api_v3_business_search&utm_source=caQpq7D94Y91yZnfu7m19Q", "review_count": 5, "categories": [{"alias": "grocery", "title": "Grocery"}, {"alias": "pharmacy", "title": "Pharmacy"}], "rating": 2.0, "coordinates": {"latitude": 49.7400197, "longitude": -123.1332963}, "transactions": [], "location": {"address1": "1900 Garibaldi Way", "address2": "", "address3": null, "city": "Squamish", "zip_code": "V8B 0P9", "country": "CA", "state": "BC", "display_address": ["1900 Garibaldi Way", "Squamish, BC V8B 0P9", "Canada"]}, "phone": "+16048986815", "display_phone": "+1 604-898-6815", "distance": 2543.205012504306}, {"id": "RHcHCLNxNqaUdhnJlDzzxA", "alias": "maples-sugar-shack-squamish", "name": "Maples' Sugar Shack", "image_url": "", "is_closed": false, "url": "https://www.yelp.com/biz/maples-sugar-shack-squamish?adjust_creative=caQpq7D94Y91yZnfu7m19Q&utm_campaign=yelp_api_v3&utm_medium=api_v3_business_search&utm_source=caQpq7D94Y91yZnfu7m19Q", "review_count": 2, "categories": [{"alias": "candy", "title": "Candy Stores"}], "rating": 4.0, "coordinates": {"latitude": 49.69854, "longitude": -123.15505}, "transactions": [], "location": {"address1": "", "address2": "", "address3": "", "city": "Squamish", "zip_code": "V0N 1T0", "country": "CA", "state": "BC", "display_address": ["Squamish, BC V0N 1T0", "Canada"]}, "phone": "+16049666789", "display_phone": "+1 604-966-6789", "distance": 2021.8670926495686}, {"id": "rBOhEXEfh7RcOp0ZmCNClg", "alias": "bc-liquor-store-squamish", "name": "BC Liquor Store", "image_url": "https://s3-media3.fl.yelpcdn.com/bphoto/-UJPLrmO3OVZW14Yf5WJpg/o.jpg", "is_closed": false, "url": "https://www.yelp.com/biz/bc-liquor-store-squamish?adjust_creative=caQpq7D94Y91yZnfu7m19Q&utm_campaign=yelp_api_v3&utm_medium=api_v3_business_search&utm_source=caQpq7D94Y91yZnfu7m19Q", "review_count": 2, "categories": [{"alias": "beer_and_wine", "title": "Beer, Wine & Spirits"}], "rating": 3.5, "coordinates": {"latitude": 49.7373677453188, "longitude": -123.131534057361}, "transactions": [], "location": {"address1": "40204 Glenalder Place", "address2": "", "address3": "", "city": "Squamish", "zip_code": "V8B 0G2", "country": "CA", "state": "BC", "display_address": ["40204 Glenalder Place", "Squamish, BC V8B 0G2", "Canada"]}, "phone": "+16048923955", "display_phone": "+1 604-892-3955", "distance": 2325.0084964190423}, {"id": "be7RJZCQgfnffl-u4vWtWA", "alias": "valleycliffe-general-store-squamish-2", "name": "ValleyCliffe General Store", "image_url": "https://s3-media4.fl.yelpcdn.com/bphoto/yYDuls26R15-j9xtbkX3Cw/o.jpg", "is_closed": false, "url": "https://www.yelp.com/biz/valleycliffe-general-store-squamish-2?adjust_creative=caQpq7D94Y91yZnfu7m19Q&utm_campaign=yelp_api_v3&utm_medium=api_v3_business_search&utm_source=caQpq7D94Y91yZnfu7m19Q", "review_count": 1, "categories": [{"alias": "convenience", "title": "Convenience Stores"}], "rating": 4.0, "coordinates": {"latitude": 49.7014044, "longitude": -123.132368}, "transactions": [], "price": "$", "location": {"address1": "104-1909 Maple Drive", "address2": "", "address3": "", "city": "Squamish", "zip_code": "V8B 0C2", "country": "CA", "state": "BC", "display_address": ["104-1909 Maple Drive", "Squamish, BC V8B 0C2", "Canada"]}, "phone": "+16048925421", "display_phone": "+1 604-892-5421", "distance": 2161.377940151175}, {"id": "m94ZZhGXUivV98NzdXJ_SQ", "alias": "kitchen-quickies-squamish-2", "name": "Kitchen Quickies", "image_url": "https://s3-media4.fl.yelpcdn.com/bphoto/1nxQVhz52YvI5sL0z0ytbg/o.jpg", "is_closed": false, "url": "https://www.yelp.com/biz/kitchen-quickies-squamish-2?adjust_creative=caQpq7D94Y91yZnfu7m19Q&utm_campaign=yelp_api_v3&utm_medium=api_v3_business_search&utm_source=caQpq7D94Y91yZnfu7m19Q", "review_count": 2, "categories": [{"alias": "grocery", "title": "Grocery"}], "rating": 3.0, "coordinates": {"latitude": 49.7378986224463, "longitude": -123.133511092407}, "transactions": [], "location": {"address1": "40226 Glenalder Place", "address2": "", "address3": "", "city": "Squamish", "zip_code": "V8B 0G2", "country": "CA", "state": "BC", "display_address": ["40226 Glenalder Place", "Squamish, BC V8B 0G2", "Canada"]}, "phone": "+16048150777", "display_phone": "+1 604-815-0777", "distance": 2318.8310872430475}, {"id": "XGeCZ5CM0540CPiczTQpJQ", "alias": "that-irish-place-squamish", "name": "That Irish Place", "image_url": "https://s3-media1.fl.yelpcdn.com/bphoto/SMQZTjUakT0Owk2ibwPFXw/o.jpg", "is_closed": false, "url": "https://www.yelp.com/biz/that-irish-place-squamish?adjust_creative=caQpq7D94Y91yZnfu7m19Q&utm_campaign=yelp_api_v3&utm_medium=api_v3_business_search&utm_source=caQpq7D94Y91yZnfu7m19Q", "review_count": 3, "categories": [{"alias": "irish_pubs", "title": "Irish Pub"}], "rating": 3.0, "coordinates": {"latitude": 49.7396786456065, "longitude": -123.133473202606}, "transactions": [], "location": {"address1": "40330 Tantalus Way", "address2": "", "address3": null, "city": "Squamish", "zip_code": "V0N 1T0", "country": "CA", "state": "BC", "display_address": ["40330 Tantalus Way", "Squamish, BC V0N 1T0", "Canada"]}, "phone": "+16047102405", "display_phone": "+1 604-710-2405", "distance": 2503.2520158210727}], "total": 65, "region": {"center": {"longitude": -123.1460952758789, "latitude": 49.71869684075233}}}